HoloLrn/HoloLrn.py
HoloLrn/__init__.py
hololrn-0.1.0.dist-info/METADATA
hololrn-0.1.0.dist-info/WHEEL
hololrn-0.1.0.dist-info/top_level.txt
hololrn-0.1.0.dist-info/RECORD
