Metadata-Version: 2.4
Name: HoloLrn
Version: 0.1.0
Summary: A modern way to allow your AI to learn from every interaction
Author: Tristan McBride Sr.
Author-email: "Tristan McBride Sr." <142635792+TristanMcBrideSr@users.noreply.github.com>
Maintainer-email: "Tristan McBride Sr." <142635792+TristanMcBrideSr@users.noreply.github.com>
License-Expression: Apache-2.0
Project-URL: Homepage, https://github.com/TristanMcBrideSr
Keywords: AI,Agents,Skills,Tools,Learning,Productivity,Automation
Classifier: Programming Language :: Python :: 3
Classifier: Operating System :: OS Independent
Classifier: Intended Audience :: Developers
Requires-Python: >=3.10
Requires-Dist: rapidfuzz
Requires-Dist: python-dotenv
Requires-Dist: google-genai
Requires-Dist: SynLrn
Dynamic: author
